{
  "version": 2,
  "extractor": "papercropper",
  "tables": [
    {
      "url": "assets/tables/arxiv/2607.16603v1/table-001.webp",
      "caption": "",
      "page": 0,
      "index": 1,
      "width": 807,
      "height": 388,
      "label": "Table"
    },
    {
      "url": "assets/tables/arxiv/2607.16603v1/table-002.webp",
      "caption": "",
      "page": 0,
      "index": 2,
      "width": 914,
      "height": 394,
      "label": "Table"
    },
    {
      "url": "assets/tables/arxiv/2607.16603v1/table-003.webp",
      "caption": "",
      "page": 0,
      "index": 3,
      "width": 692,
      "height": 384,
      "label": "Table"
    },
    {
      "url": "assets/tables/arxiv/2607.16603v1/table-004.webp",
      "caption": "",
      "page": 0,
      "index": 4,
      "width": 872,
      "height": 277,
      "label": "Table"
    },
    {
      "url": "assets/tables/arxiv/2607.16603v1/table-005.webp",
      "caption": "",
      "page": 0,
      "index": 5,
      "width": 736,
      "height": 613,
      "label": "Table"
    },
    {
      "url": "assets/tables/arxiv/2607.16603v1/table-006.webp",
      "caption": "",
      "page": 0,
      "index": 6,
      "width": 611,
      "height": 220,
      "label": "Table"
    },
    {
      "url": "assets/tables/arxiv/2607.16603v1/table-007.webp",
      "caption": "",
      "page": 0,
      "index": 7,
      "width": 790,
      "height": 377,
      "label": "Table"
    },
    {
      "url": "assets/tables/arxiv/2607.16603v1/table-008.webp",
      "caption": "",
      "page": 0,
      "index": 8,
      "width": 872,
      "height": 310,
      "label": "Table"
    }
  ]
}